dlong/__init__.py
dlong/_version.py
dlong/types.py
dlong/core/__init__.py
dlong/core/damages.py
dlong/core/discounts.py
dlong/core/recipes.py
dlong-0.2.0.dist-info/METADATA
dlong-0.2.0.dist-info/WHEEL
dlong-0.2.0.dist-info/licenses/LICENSE
dlong-0.2.0.dist-info/RECORD
