Metadata-Version: 2.1
Name: dlong
Version: 0.2.0
Summary: Prototype framework for projected socio-economic climate damages
Project-URL: Homepage, https://github.com/brews/dlong
Project-URL: Documentation, https://github.com/brews/dlong
Project-URL: Source, https://github.com/brews/dlong
Project-URL: Bug Tracker, https://github.com/brews/dlong/issues
License-File: LICENSE
Classifier: Intended Audience :: Developers
Classifier: Intended Audience :: Science/Research
Classifier: License :: OSI Approved :: Apache Software License
Classifier: Natural Language :: English
Classifier: Operating System :: OS Independent
Classifier: Programming Language :: Python :: 3
Classifier: Topic :: Scientific/Engineering
Requires-Python: >=3.8
Requires-Dist: xarray
Provides-Extra: test
Requires-Dist: black; extra == 'test'
Requires-Dist: mypy; extra == 'test'
Requires-Dist: pytest; extra == 'test'
Requires-Dist: pytest-cov; extra == 'test'
Requires-Dist: ruff; extra == 'test'
